[
    { "date": "2026-06-11", "team1": "Mexico", "team2": "South Africa", "venue_city": "Mexico City", "venue_stadium": "Estadio Azteca" },
    { "date": "2026-06-11", "team1": "South Korea", "team2": "Czechia", "venue_city": "Guadalajara", "venue_stadium": "Estadio Akron" },
    { "date": "2026-06-12", "team1": "Canada", "team2": "Bosnia and Herzegovina", "venue_city": "Toronto", "venue_stadium": "BMO Field" },
    { "date": "2026-06-13", "team1": "Qatar", "team2": "Switzerland", "venue_city": "Vancouver", "venue_stadium": "BC Place" },
    { "date": "2026-06-13", "team1": "Brazil", "team2": "Morocco", "venue_city": "Los Angeles", "venue_stadium": "SoFi Stadium" },
    { "date": "2026-06-13", "team1": "Haiti", "team2": "Scotland", "venue_city": "San Francisco", "venue_stadium": "Levi's Stadium" },
    { "date": "2026-06-13", "team1": "USA", "team2": "Paraguay", "venue_city": "Dallas", "venue_stadium": "AT&T Stadium" },
    { "date": "2026-06-14", "team1": "Australia", "team2": "Turkiye", "venue_city": "Houston", "venue_stadium": "NRG Stadium" },
    { "date": "2026-06-15", "team1": "Germany", "team2": "Curacao", "venue_city": "Kansas City", "venue_stadium": "Arrowhead Stadium" },
    { "date": "2026-06-15", "team1": "Ivory Coast", "team2": "Ecuador", "venue_city": "Atlanta", "venue_stadium": "Mercedes-Benz Stadium" },
    { "date": "2026-06-16", "team1": "Netherlands", "team2": "Japan", "venue_city": "Miami", "venue_stadium": "Hard Rock Stadium" },
    { "date": "2026-06-16", "team1": "Sweden", "team2": "Tunisia", "venue_city": "Seattle", "venue_stadium": "Lumen Field" },
    { "date": "2026-06-17", "team1": "Belgium", "team2": "Egypt", "venue_city": "Mexico City", "venue_stadium": "Estadio Azteca" },
    { "date": "2026-06-17", "team1": "Iran", "team2": "New Zealand", "venue_city": "Guadalajara", "venue_stadium": "Estadio Akron" },
    { "date": "2026-06-18", "team1": "Spain", "team2": "Cape Verde", "venue_city": "Toronto", "venue_stadium": "BMO Field" },
    { "date": "2026-06-18", "team1": "Saudi Arabia", "team2": "Uruguay", "venue_city": "Vancouver", "venue_stadium": "BC Place" },
    { "date": "2026-06-19", "team1": "France", "team2": "Senegal", "venue_city": "Los Angeles", "venue_stadium": "SoFi Stadium" },
    { "date": "2026-06-19", "team1": "Iraq", "team2": "Norway", "venue_city": "San Francisco", "venue_stadium": "Levi's Stadium" },
    { "date": "2026-06-20", "team1": "Argentina", "team2": "Algeria", "venue_city": "Dallas", "venue_stadium": "AT&T Stadium" },
    { "date": "2026-06-20", "team1": "Austria", "team2": "Jordan", "venue_city": "Houston", "venue_stadium": "NRG Stadium" },
    { "date": "2026-06-21", "team1": "Portugal", "team2": "DR Congo", "venue_city": "Kansas City", "venue_stadium": "Arrowhead Stadium" },
    { "date": "2026-06-21", "team1": "Uzbekistan", "team2": "Colombia", "venue_city": "Atlanta", "venue_stadium": "Mercedes-Benz Stadium" },
    { "date": "2026-06-22", "team1": "England", "team2": "Croatia", "venue_city": "Miami", "venue_stadium": "Hard Rock Stadium" },
    { "date": "2026-06-22", "team1": "Ghana", "team2": "Panama", "venue_city": "Seattle", "venue_stadium": "Lumen Field" },
  
    { "date": "2026-06-23", "team1": "South Africa", "team2": "South Korea", "venue_city": "Mexico City", "venue_stadium": "Estadio Azteca" },
    { "date": "2026-06-23", "team1": "Czechia", "team2": "Mexico", "venue_city": "Guadalajara", "venue_stadium": "Estadio Akron" },
    { "date": "2026-06-23", "team1": "Bosnia and Herzegovina", "team2": "Qatar", "venue_city": "Toronto", "venue_stadium": "BMO Field" },
    { "date": "2026-06-23", "team1": "Switzerland", "team2": "Canada", "venue_city": "Vancouver", "venue_stadium": "BC Place" },
    { "date": "2026-06-24", "team1": "Morocco", "team2": "Haiti", "venue_city": "Los Angeles", "venue_stadium": "SoFi Stadium" },
    { "date": "2026-06-24", "team1": "Scotland", "team2": "Brazil", "venue_city": "San Francisco", "venue_stadium": "Levi's Stadium" },
    { "date": "2026-06-24", "team1": "Paraguay", "team2": "Australia", "venue_city": "Dallas", "venue_stadium": "AT&T Stadium" },
    { "date": "2026-06-24", "team1": "Turkiye", "team2": "USA", "venue_city": "Houston", "venue_stadium": "NRG Stadium" },
    { "date": "2026-06-25", "team1": "Curacao", "team2": "Ivory Coast", "venue_city": "Kansas City", "venue_stadium": "Arrowhead Stadium" },
    { "date": "2026-06-25", "team1": "Ecuador", "team2": "Germany", "venue_city": "Atlanta", "venue_stadium": "Mercedes-Benz Stadium" },
    { "date": "2026-06-25", "team1": "Japan", "team2": "Sweden", "venue_city": "Miami", "venue_stadium": "Hard Rock Stadium" },
    { "date": "2026-06-25", "team1": "Tunisia", "team2": "Netherlands", "venue_city": "Seattle", "venue_stadium": "Lumen Field" },
    { "date": "2026-06-26", "team1": "Egypt", "team2": "Iran", "venue_city": "Mexico City", "venue_stadium": "Estadio Azteca" },
    { "date": "2026-06-26", "team1": "New Zealand", "team2": "Belgium", "venue_city": "Guadalajara", "venue_stadium": "Estadio Akron" },
    { "date": "2026-06-26", "team1": "Cape Verde", "team2": "Saudi Arabia", "venue_city": "Toronto", "venue_stadium": "BMO Field" },
    { "date": "2026-06-26", "team1": "Uruguay", "team2": "Spain", "venue_city": "Vancouver", "venue_stadium": "BC Place" },
    { "date": "2026-06-27", "team1": "Senegal", "team2": "Iraq", "venue_city": "Los Angeles", "venue_stadium": "SoFi Stadium" },
    { "date": "2026-06-27", "team1": "Norway", "team2": "France", "venue_city": "San Francisco", "venue_stadium": "Levi's Stadium" },
    { "date": "2026-06-27", "team1": "Algeria", "team2": "Austria", "venue_city": "Dallas", "venue_stadium": "AT&T Stadium" },
    { "date": "2026-06-27", "team1": "Jordan", "team2": "Argentina", "venue_city": "Houston", "venue_stadium": "NRG Stadium" },
    { "date": "2026-06-28", "team1": "DR Congo", "team2": "Uzbekistan", "venue_city": "Kansas City", "venue_stadium": "Arrowhead Stadium" },
    { "date": "2026-06-28", "team1": "Colombia", "team2": "Portugal", "venue_city": "Atlanta", "venue_stadium": "Mercedes-Benz Stadium" },
    { "date": "2026-06-28", "team1": "Croatia", "team2": "Ghana", "venue_city": "Miami", "venue_stadium": "Hard Rock Stadium" },
    { "date": "2026-06-28", "team1": "Panama", "team2": "England", "venue_city": "Seattle", "venue_stadium": "Lumen Field" },

    { "date": "2026-06-29", "team1": "Mexico", "team2": "South Korea", "venue_city": "Mexico City", "venue_stadium": "Estadio Azteca" },
    { "date": "2026-06-29", "team1": "Czech Republic", "team2": "South Africa", "venue_city": "Guadalajara", "venue_stadium": "Estadio Akron" },
    { "date": "2026-06-29", "team1": "Canada", "team2": "Qatar", "venue_city": "Toronto", "venue_stadium": "BMO Field" },
    { "date": "2026-06-29", "team1": "Switzerland", "team2": "Bosnia and Herzegovina", "venue_city": "Vancouver", "venue_stadium": "BC Place" },
    { "date": "2026-06-30", "team1": "Brazil", "team2": "Haiti", "venue_city": "Los Angeles", "venue_stadium": "SoFi Stadium" },
    { "date": "2026-06-30", "team1": "Scotland", "team2": "Morocco", "venue_city": "San Francisco", "venue_stadium": "Levi's Stadium" },
    { "date": "2026-06-30", "team1": "United States", "team2": "Australia", "venue_city": "Dallas", "venue_stadium": "AT&T Stadium" },
    { "date": "2026-06-30", "team1": "Turkey", "team2": "Paraguay", "venue_city": "Houston", "venue_stadium": "NRG Stadium" },
    { "date": "2026-07-01", "team1": "Germany", "team2": "Ivory Coast", "venue_city": "Kansas City", "venue_stadium": "Arrowhead Stadium" },
    { "date": "2026-07-01", "team1": "Ecuador", "team2": "Curacao", "venue_city": "Atlanta", "venue_stadium": "Mercedes-Benz Stadium" },
    { "date": "2026-07-01", "team1": "Netherlands", "team2": "Sweden", "venue_city": "Miami", "venue_stadium": "Hard Rock Stadium" },
    { "date": "2026-07-01", "team1": "Tunisia", "team2": "Japan", "venue_city": "Seattle", "venue_stadium": "Lumen Field" },
    { "date": "2026-07-02", "team1": "Belgium", "team2": "Iran", "venue_city": "Mexico City", "venue_stadium": "Estadio Azteca" },
    { "date": "2026-07-02", "team1": "New Zealand", "team2": "Egypt", "venue_city": "Guadalajara", "venue_stadium": "Estadio Akron" },
    { "date": "2026-07-02", "team1": "Spain", "team2": "Saudi Arabia", "venue_city": "Toronto", "venue_stadium": "BMO Field" },
    { "date": "2026-07-02", "team1": "Uruguay", "team2": "Cape Verde", "venue_city": "Vancouver", "venue_stadium": "BC Place" },
    { "date": "2026-07-03", "team1": "France", "team2": "Iraq", "venue_city": "Los Angeles", "venue_stadium": "SoFi Stadium" },
    { "date": "2026-07-03", "team1": "Norway", "team2": "Senegal", "venue_city": "San Francisco", "venue_stadium": "Levi's Stadium" },
    { "date": "2026-07-03", "team1": "Argentina", "team2": "Austria", "venue_city": "Dallas", "venue_stadium": "AT&T Stadium" },
    { "date": "2026-07-03", "team1": "Jordan", "team2": "Algeria", "venue_city": "Houston", "venue_stadium": "NRG Stadium" },
    { "date": "2026-07-04", "team1": "Portugal", "team2": "Uzbekistan", "venue_city": "Kansas City", "venue_stadium": "Arrowhead Stadium" },
    { "date": "2026-07-04", "team1": "Colombia", "team2": "Congo DR", "venue_city": "Atlanta", "venue_stadium": "Mercedes-Benz Stadium" },
    { "date": "2026-07-04", "team1": "England", "team2": "Ghana", "venue_city": "Miami", "venue_stadium": "Hard Rock Stadium" },
    { "date": "2026-07-04", "team1": "Panama", "team2": "Croatia", "venue_city": "Seattle", "venue_stadium": "Lumen Field" }
  ]